routerflu/__init__.py
routerflu/main.py
routerflu/prompts.py
routerflu-2025.12.21112723.dist-info/METADATA
routerflu-2025.12.21112723.dist-info/WHEEL
routerflu-2025.12.21112723.dist-info/top_level.txt
routerflu-2025.12.21112723.dist-info/RECORD
