Metadata-Version: 2.4
Name: routerflu
Version: 2025.12.21112723
Summary: A new package is designed to streamline the interaction with large language models like Claude Code via OpenRouter by accepting user prompts in natural language, processing them through structured mes
Author-email: routerflu <hi@eugene.plus>
License: MIT
Project-URL: Homepage, https://github.com/chigwell/routerflu
Requires-Python: >=3.9
Requires-Dist: langchain-llm7>=0.0.0
Requires-Dist: llmatch-messages>=0.0.0
Requires-Dist: langchain-core>=0.3.0
